.coveragerc
.git_archival.txt
.gitignore
LICENSE
README.md
setup.cfg
setup.py
.github/ISSUE_TEMPLATE.md
.github/PULL_REQUEST_TEMPLATE.md
.github/workflows/ci.yaml
.github/workflows/deploy-sdist.yaml
bin/viirs_af_runner.py
continuous_integration/environment.yaml
etc/viirs_af_config.yaml.template
pytroll_active_fire_runner.egg-info/PKG-INFO
pytroll_active_fire_runner.egg-info/SOURCES.txt
pytroll_active_fire_runner.egg-info/dependency_links.txt
pytroll_active_fire_runner.egg-info/not-zip-safe
pytroll_active_fire_runner.egg-info/requires.txt
pytroll_active_fire_runner.egg-info/top_level.txt
viirs_active_fires/__init__.py
viirs_active_fires/utils.py
viirs_active_fires/tests/test_utils.py