Metadata-Version: 1.1
Name: pytroll-active-fire-runner
Version: 0.2.1
Summary: Pytroll runner for the VIIRS active fires
Home-page: https://github.com/pytroll/pytroll-active-fire-runner
Author: Adam Dybroe
Author-email: adam.dybroe@smhi.se
License: UNKNOWN
Platform: UNKNOWN
Classifier: Development Status :: 3 - Alpha
Classifier: Intended Audience :: Science/Research
Classifier: License :: OSI Approved :: GNU General Public License v3 or later (GPLv3+)
Classifier: Operating System :: OS Independent
Classifier: Programming Language :: Python
Classifier: Topic :: Scientific/Engineering
